{
  "numerico": {
    "foreground": "#c48aff"
  },
  "atribuicao": {
    "foreground": "#b8ff75"
  },
  "loops": {
    "foreground": "#f94fff"
  },
  "lista": {
    "foreground": "#91fdff"
  },
  "logico": {
    "foreground": "#ff5473"
  },
  "entrada": {
    "foreground": "#ff5473"
  },
  "exibicao": {
    "foreground": "#78aeff"
  },
  "tempo": {
    "foreground": "#91fdff"
  },
  "condicionais": {
    "foreground": "#f94fff"
  },
  "contas": {
    "foreground": "#ff5473"
  },
  "string": {
    "foreground": "#fff891"
  },
  "comentario": {
    "foreground": "#8cbd7d"
  },
  "pare": {
    "foreground": "#ff1212"
  }
}
